{
  "legislative_session": "2026RS",
  "identifier": "HB333",
  "title": "AN ACT relating to housing.",
  "from_organization": "~{\"classification\": \"lower\"}",
  "classification": [
    "bill"
  ],
  "subject": [
    "Housing, Building, And Construction",
    "Land Use",
    "Local Government",
    "Local Mandate",
    "Planning And Zoning",
    "Property",
    "Religion"
  ],
  "abstracts": [
    {
      "note": "Summary of Original Version",
      "abstract": "Create a new section of KRS Chapter 100 to define terms; make affordable housing developed by a religious developer a permitted use and require only a ministerial review by a planning unit for compliance with the section; include requirements that an affordable housing development must meet including that it be on property owned by a religious institution prior to January 1, 2026, exclusively contains affordable housing, be less than 24 units and be located only on a parcel in certain zones, and to have obtained all other permits; require a religious institution that does not continue to qualify to seek approval from a planning unit; allow the Kentucky Housing Corporation to advise religious developers regarding affordable housing developments; allow homeless shelters operated by a religious institution to be permitted uses in commercial or business zones."
    }
  ],
  "other_titles": [],
  "other_identifiers": [
    {
      "identifier": "ocd-bill-ky-2026rs-hb333"
    }
  ],
  "actions": [
    {
      "description": "introduced in House",
      "date": "2026-01-13T05:00:00+00:00",
      "organization_id": "~{\"classification\": \"lower\"}",
      "classification": [
        "introduction"
      ],
      "related_entities": [],
      "_processing": {
        "log_file_created": "2026-07-15T13:54:54Z"
      }
    },
    {
      "description": "to Committee on Committees (H)",
      "date": "2026-01-13T05:00:00+00:00",
      "organization_id": "~{\"classification\": \"lower\"}",
      "classification": [
        "referral-committee"
      ],
      "related_entities": [],
      "_processing": {
        "log_file_created": "2026-07-15T13:54:54Z"
      }
    },
    {
      "description": "to Local Government (H)",
      "date": "2026-01-21T05:00:00+00:00",
      "organization_id": "~{\"classification\": \"lower\"}",
      "classification": [
        "referral-committee"
      ],
      "related_entities": [],
      "_processing": {
        "log_file_created": "2026-07-15T13:54:54Z"
      }
    },
    {
      "description": "reported favorably, 1st reading, to Calendar",
      "date": "2026-02-03T05:00:00+00:00",
      "organization_id": "~{\"classification\": \"lower\"}",
      "classification": [
        "committee-passage"
      ],
      "related_entities": [],
      "_processing": {
        "log_file_created": "2026-07-15T13:54:54Z"
      }
    },
    {
      "description": "2nd reading, to Rules",
      "date": "2026-02-04T05:00:00+00:00",
      "organization_id": "~{\"classification\": \"lower\"}",
      "classification": [
        "reading-2"
      ],
      "related_entities": [],
      "_processing": {
        "log_file_created": "2026-07-15T13:54:54Z"
      }
    },
    {
      "description": "posted for passage in the Regular Orders of the Day for Friday, February 06 2026",
      "date": "2026-02-05T05:00:00+00:00",
      "organization_id": "~{\"classification\": \"lower\"}",
      "classification": [],
      "related_entities": [],
      "_processing": {
        "log_file_created": "2026-07-15T13:54:54Z"
      }
    },
    {
      "description": "3rd reading, passed 90-1-1",
      "date": "2026-02-06T05:00:00+00:00",
      "organization_id": "~{\"classification\": \"lower\"}",
      "classification": [
        "passage",
        "reading-3"
      ],
      "related_entities": [],
      "_processing": {
        "log_file_created": "2026-07-15T13:54:54Z"
      }
    },
    {
      "description": "received in Senate",
      "date": "2026-02-09T05:00:00+00:00",
      "organization_id": "~{\"classification\": \"upper\"}",
      "classification": [],
      "related_entities": [],
      "_processing": {
        "log_file_created": "2026-07-15T13:54:54Z"
      }
    },
    {
      "description": "to Committee on Committees (S)",
      "date": "2026-02-09T05:00:00+00:00",
      "organization_id": "~{\"classification\": \"upper\"}",
      "classification": [
        "referral-committee"
      ],
      "related_entities": [],
      "_processing": {
        "log_file_created": "2026-07-15T13:54:54Z"
      }
    },
    {
      "description": "to Economic Development, Tourism, & Labor (S)",
      "date": "2026-03-11T04:00:00+00:00",
      "organization_id": "~{\"classification\": \"upper\"}",
      "classification": [
        "referral-committee"
      ],
      "related_entities": [],
      "_processing": {
        "log_file_created": "2026-07-15T13:54:54Z"
      }
    },
    {
      "description": "reported favorably, 1st reading, to Consent Calendar",
      "date": "2026-03-12T04:00:00+00:00",
      "organization_id": "~{\"classification\": \"lower\"}",
      "classification": [
        "committee-passage"
      ],
      "related_entities": [],
      "_processing": {
        "log_file_created": "2026-07-15T13:54:54Z"
      }
    },
    {
      "description": "2nd reading, to Rules as a consent bill",
      "date": "2026-03-13T04:00:00+00:00",
      "organization_id": "~{\"classification\": \"lower\"}",
      "classification": [
        "reading-2"
      ],
      "related_entities": [],
      "_processing": {
        "log_file_created": "2026-07-15T13:54:54Z"
      }
    },
    {
      "description": "posted for passage in the Consent Orders of the Day for Tuesday, March 24 2026",
      "date": "2026-03-20T04:00:00+00:00",
      "organization_id": "~{\"classification\": \"lower\"}",
      "classification": [],
      "related_entities": [],
      "_processing": {
        "log_file_created": "2026-07-15T13:54:54Z"
      }
    },
    {
      "description": "passed over and retained in the Consent Orders of the Day",
      "date": "2026-03-24T04:00:00+00:00",
      "organization_id": "~{\"classification\": \"lower\"}",
      "classification": [
        "passage"
      ],
      "related_entities": [],
      "_processing": {
        "log_file_created": "2026-07-15T13:54:54Z"
      }
    },
    {
      "description": "3rd reading, passed 34-4",
      "date": "2026-03-25T04:00:00+00:00",
      "organization_id": "~{\"classification\": \"lower\"}",
      "classification": [
        "passage",
        "reading-3"
      ],
      "related_entities": [],
      "_processing": {
        "log_file_created": "2026-07-15T13:54:54Z"
      }
    },
    {
      "description": "received in House",
      "date": "2026-03-26T04:00:00+00:00",
      "organization_id": "~{\"classification\": \"lower\"}",
      "classification": [],
      "related_entities": [],
      "_processing": {
        "log_file_created": "2026-07-15T13:54:54Z"
      }
    },
    {
      "description": "enrolled, signed by Speaker of the House",
      "date": "2026-03-26T04:00:00+00:00",
      "organization_id": "~{\"classification\": \"lower\"}",
      "classification": [
        "passage"
      ],
      "related_entities": [],
      "_processing": {
        "log_file_created": "2026-07-15T13:54:54Z"
      }
    },
    {
      "description": "enrolled, signed by President of the Senate",
      "date": "2026-03-26T04:00:00+00:00",
      "organization_id": "~{\"classification\": \"upper\"}",
      "classification": [
        "passage"
      ],
      "related_entities": [],
      "_processing": {
        "log_file_created": "2026-07-15T13:54:54Z"
      }
    },
    {
      "description": "delivered to Governor",
      "date": "2026-03-26T04:00:00+00:00",
      "organization_id": "~{\"classification\": \"lower\"}",
      "classification": [],
      "related_entities": [],
      "_processing": {
        "log_file_created": "2026-07-15T13:54:54Z"
      }
    },
    {
      "description": "signed by Governor (Acts Ch. 37)",
      "date": "2026-04-07T04:00:00+00:00",
      "organization_id": "~{\"classification\": \"lower\"}",
      "classification": [
        "executive-signature"
      ],
      "related_entities": [],
      "_processing": {
        "log_file_created": "2026-07-15T13:54:54Z"
      }
    }
  ],
  "sponsorships": [
    {
      "name": "M. Pollock",
      "classification": "primary",
      "entity_type": "person",
      "primary": true,
      "person_id": "~{\"name\": \"M. Pollock\"}",
      "organization_id": null
    },
    {
      "name": "B. Chester-Burton",
      "classification": "primary",
      "entity_type": "person",
      "primary": true,
      "person_id": "~{\"name\": \"B. Chester-Burton\"}",
      "organization_id": null
    },
    {
      "name": "M. Clines",
      "classification": "primary",
      "entity_type": "person",
      "primary": true,
      "person_id": "~{\"name\": \"M. Clines\"}",
      "organization_id": null
    },
    {
      "name": "D. Elliott",
      "classification": "primary",
      "entity_type": "person",
      "primary": true,
      "person_id": "~{\"name\": \"D. Elliott\"}",
      "organization_id": null
    },
    {
      "name": "A. Gentry",
      "classification": "primary",
      "entity_type": "person",
      "primary": true,
      "person_id": "~{\"name\": \"A. Gentry\"}",
      "organization_id": null
    },
    {
      "name": "D. Grossberg",
      "classification": "primary",
      "entity_type": "person",
      "primary": true,
      "person_id": "~{\"name\": \"D. Grossberg\"}",
      "organization_id": null
    },
    {
      "name": "K. Moser",
      "classification": "primary",
      "entity_type": "person",
      "primary": true,
      "person_id": "~{\"name\": \"K. Moser\"}",
      "organization_id": null
    },
    {
      "name": "S. Stalker",
      "classification": "primary",
      "entity_type": "person",
      "primary": true,
      "person_id": "~{\"name\": \"S. Stalker\"}",
      "organization_id": null
    },
    {
      "name": "P. Stevenson",
      "classification": "primary",
      "entity_type": "person",
      "primary": true,
      "person_id": "~{\"name\": \"P. Stevenson\"}",
      "organization_id": null
    },
    {
      "name": "J. Watkins",
      "classification": "primary",
      "entity_type": "person",
      "primary": true,
      "person_id": "~{\"name\": \"J. Watkins\"}",
      "organization_id": null
    },
    {
      "name": "W. Williams",
      "classification": "primary",
      "entity_type": "person",
      "primary": true,
      "person_id": "~{\"name\": \"W. Williams\"}",
      "organization_id": null
    },
    {
      "name": "S. Witten",
      "classification": "primary",
      "entity_type": "person",
      "primary": true,
      "person_id": "~{\"name\": \"S. Witten\"}",
      "organization_id": null
    }
  ],
  "related_bills": [],
  "versions": [
    {
      "note": "Acts Chapter 37",
      "links": [
        {
          "url": "https://apps.legislature.ky.gov/law/acts/26RS/documents/0037.pdf",
          "media_type": "application/pdf"
        }
      ],
      "date": "",
      "classification": ""
    },
    {
      "note": "Current/Final",
      "links": [
        {
          "url": "https://apps.legislature.ky.gov/recorddocuments/bill/26RS/hb333/bill.pdf",
          "media_type": "application/pdf"
        }
      ],
      "date": "",
      "classification": ""
    },
    {
      "note": "Introduced",
      "links": [
        {
          "url": "https://apps.legislature.ky.gov/recorddocuments/bill/26RS/hb333/orig_bill.pdf",
          "media_type": "application/pdf"
        }
      ],
      "date": "",
      "classification": ""
    }
  ],
  "documents": [
    {
      "note": "Fiscal Note",
      "links": [
        {
          "url": "https://apps.legislature.ky.gov/recorddocuments/note/26RS/hb333/LM.pdf",
          "media_type": "application/pdf"
        }
      ],
      "date": "",
      "classification": ""
    }
  ],
  "citations": [],
  "sources": [
    {
      "url": "https://apps.legislature.ky.gov/record/26RS/hb333.html",
      "note": ""
    }
  ],
  "extras": {
    "BDR": "982"
  },
  "jurisdiction": {
    "id": "ocd-jurisdiction/country:us/state:ky/government",
    "name": "Kentucky",
    "classification": "state",
    "division_id": "ocd-division/country:us/state:ky"
  },
  "_processing": {
    "logs_latest_update": "2026-07-15T13:54:54Z",
    "text_extraction_latest_update": "2026-07-21T06:25:37.323549Z"
  }
}