{
  "legislative_session": "2026RS",
  "identifier": "SR298",
  "title": "A RESOLUTION honoring the contributions of Christian women leaders in the Commonwealth of Kentucky through She Leads Kentucky.",
  "from_organization": "~{\"classification\": \"upper\"}",
  "classification": [
    "resolution"
  ],
  "subject": [
    "Commendations And Recognitions",
    "Religion",
    "Women"
  ],
  "abstracts": [
    {
      "note": "Summary of Original Version",
      "abstract": "Honor the contributions of Christian women leaders in the Commonwealth of Kentucky through She Leads Kentucky."
    }
  ],
  "other_titles": [],
  "other_identifiers": [
    {
      "identifier": "ocd-bill-ky-2026rs-sr298"
    }
  ],
  "actions": [
    {
      "description": "introduced in Senate",
      "date": "2026-04-14T04:00:00+00:00",
      "organization_id": "~{\"classification\": \"upper\"}",
      "classification": [
        "introduction"
      ],
      "related_entities": [],
      "_processing": {
        "log_file_created": "2026-07-15T13:54:54Z"
      }
    },
    {
      "description": "to Committee on Committees (S)",
      "date": "2026-04-14T04:00:00+00:00",
      "organization_id": "~{\"classification\": \"upper\"}",
      "classification": [
        "referral-committee"
      ],
      "related_entities": [],
      "_processing": {
        "log_file_created": "2026-07-15T13:54:54Z"
      }
    },
    {
      "description": "to Senate Floor",
      "date": "2026-04-15T04:00:00+00:00",
      "organization_id": "~{\"classification\": \"upper\"}",
      "classification": [
        "referral-committee"
      ],
      "related_entities": [],
      "_processing": {
        "log_file_created": "2026-07-15T13:54:54Z"
      }
    },
    {
      "description": "adopted by voice vote",
      "date": "2026-04-15T04:00:00+00:00",
      "organization_id": "~{\"classification\": \"upper\"}",
      "classification": [
        "passage"
      ],
      "related_entities": [],
      "_processing": {
        "log_file_created": "2026-07-15T13:54:54Z"
      }
    }
  ],
  "sponsorships": [
    {
      "name": "L. Tichenor",
      "classification": "primary",
      "entity_type": "person",
      "primary": true,
      "person_id": "~{\"name\": \"L. Tichenor\"}",
      "organization_id": null
    }
  ],
  "related_bills": [],
  "versions": [
    {
      "note": "Current/Final",
      "links": [
        {
          "url": "https://apps.legislature.ky.gov/recorddocuments/bill/26RS/sr298/bill.pdf",
          "media_type": "application/pdf"
        }
      ],
      "date": "",
      "classification": ""
    },
    {
      "note": "Introduced",
      "links": [
        {
          "url": "https://apps.legislature.ky.gov/recorddocuments/bill/26RS/sr298/orig_bill.pdf",
          "media_type": "application/pdf"
        }
      ],
      "date": "",
      "classification": ""
    }
  ],
  "documents": [],
  "citations": [],
  "sources": [
    {
      "url": "https://apps.legislature.ky.gov/record/26RS/sr298.html",
      "note": ""
    }
  ],
  "extras": {
    "BDR": "2634"
  },
  "jurisdiction": {
    "id": "ocd-jurisdiction/country:us/state:ky/government",
    "name": "Kentucky",
    "classification": "state",
    "division_id": "ocd-division/country:us/state:ky"
  },
  "_processing": {
    "logs_latest_update": "2026-07-15T13:54:54Z"
  }
}