{
  "legislative_session": "2026RS",
  "identifier": "SB146",
  "title": "AN ACT relating to filings with the county clerk.",
  "from_organization": "~{\"classification\": \"upper\"}",
  "classification": [
    "bill"
  ],
  "subject": [
    "Circuit Clerks",
    "County Clerks",
    "Local Mandate",
    "Public Records And Reports",
    "Taxation",
    "Wills, Trusts, And Estates"
  ],
  "abstracts": [
    {
      "note": "Summary of Original Version",
      "abstract": "Amend KRS 64.012 to establish a flat fee of $33 to record a will or court-ordered name change with a county clerk; amend KRS 142.010 to establish a $4 tax on each recorded will; amend KRS 394.300 to establish timelines for retention and return of a recorded will by a county clerk; amend KRS 395.015 to authorize the clerk of the court to collect information and the applicable fee and tax on wills recorded by the court clerk; amend KRS 401.040 to authorize the clerk of the court to collect the recording fee for a court-ordered name change order on behalf of the county clerk; amend KRS 395.160 to conform."
    }
  ],
  "other_titles": [],
  "other_identifiers": [
    {
      "identifier": "ocd-bill-ky-2026rs-sb146"
    }
  ],
  "actions": [
    {
      "description": "introduced in Senate",
      "date": "2026-02-02T05:00:00+00:00",
      "organization_id": "~{\"classification\": \"upper\"}",
      "classification": [
        "introduction"
      ],
      "related_entities": [],
      "_processing": {
        "log_file_created": "2026-07-15T13:54:54Z"
      }
    },
    {
      "description": "to Committee on Committees (S)",
      "date": "2026-02-02T05:00:00+00:00",
      "organization_id": "~{\"classification\": \"upper\"}",
      "classification": [
        "referral-committee"
      ],
      "related_entities": [],
      "_processing": {
        "log_file_created": "2026-07-15T13:54:54Z"
      }
    }
  ],
  "sponsorships": [
    {
      "name": "J. Adams",
      "classification": "primary",
      "entity_type": "person",
      "primary": true,
      "person_id": "~{\"name\": \"J. Adams\"}",
      "organization_id": null
    }
  ],
  "related_bills": [],
  "versions": [
    {
      "note": "Introduced",
      "links": [
        {
          "url": "https://apps.legislature.ky.gov/recorddocuments/bill/26RS/sb146/orig_bill.pdf",
          "media_type": "application/pdf"
        }
      ],
      "date": "",
      "classification": ""
    }
  ],
  "documents": [
    {
      "note": "Fiscal Note",
      "links": [
        {
          "url": "https://apps.legislature.ky.gov/recorddocuments/note/26RS/sb146/LM.pdf",
          "media_type": "application/pdf"
        }
      ],
      "date": "",
      "classification": ""
    }
  ],
  "citations": [],
  "sources": [
    {
      "url": "https://apps.legislature.ky.gov/record/26RS/sb146.html",
      "note": ""
    }
  ],
  "extras": {
    "BDR": "412"
  },
  "jurisdiction": {
    "id": "ocd-jurisdiction/country:us/state:ky/government",
    "name": "Kentucky",
    "classification": "state",
    "division_id": "ocd-division/country:us/state:ky"
  },
  "_processing": {
    "logs_latest_update": "2026-07-15T13:54:54Z"
  }
}