{
  "legislative_session": "2026RS",
  "identifier": "HB357",
  "title": "AN ACT relating to jury duty.",
  "from_organization": "~{\"classification\": \"lower\"}",
  "classification": [
    "bill"
  ],
  "subject": [
    "Judges And Court Commissioners",
    "Juries And Jurors",
    "Teachers"
  ],
  "abstracts": [
    {
      "note": "Summary of Original Version",
      "abstract": "Amend KRS 29A.100 to require judges to excuse teachers from jury duty until the end of the school term if the Commonwealth is experiencing a teacher shortage."
    }
  ],
  "other_titles": [],
  "other_identifiers": [
    {
      "identifier": "ocd-bill-ky-2026rs-hb357"
    }
  ],
  "actions": [
    {
      "description": "introduced in House",
      "date": "2026-01-13T05:00:00+00:00",
      "organization_id": "~{\"classification\": \"lower\"}",
      "classification": [
        "introduction"
      ],
      "related_entities": [],
      "_processing": {
        "log_file_created": "2026-07-15T13:54:52Z"
      }
    },
    {
      "description": "to Committee on Committees (H)",
      "date": "2026-01-13T05:00:00+00:00",
      "organization_id": "~{\"classification\": \"lower\"}",
      "classification": [
        "referral-committee"
      ],
      "related_entities": [],
      "_processing": {
        "log_file_created": "2026-07-15T13:54:52Z"
      }
    },
    {
      "description": "to Judiciary (H)",
      "date": "2026-01-21T05:00:00+00:00",
      "organization_id": "~{\"classification\": \"lower\"}",
      "classification": [
        "referral-committee"
      ],
      "related_entities": [],
      "_processing": {
        "log_file_created": "2026-07-15T13:54:52Z"
      }
    }
  ],
  "sponsorships": [
    {
      "name": "S. Stalker",
      "classification": "primary",
      "entity_type": "person",
      "primary": true,
      "person_id": "~{\"name\": \"S. Stalker\"}",
      "organization_id": null
    },
    {
      "name": "T. Truett",
      "classification": "primary",
      "entity_type": "person",
      "primary": true,
      "person_id": "~{\"name\": \"T. Truett\"}",
      "organization_id": null
    },
    {
      "name": "T. Bojanowski",
      "classification": "primary",
      "entity_type": "person",
      "primary": true,
      "person_id": "~{\"name\": \"T. Bojanowski\"}",
      "organization_id": null
    },
    {
      "name": "A. Camuel",
      "classification": "primary",
      "entity_type": "person",
      "primary": true,
      "person_id": "~{\"name\": \"A. Camuel\"}",
      "organization_id": null
    },
    {
      "name": "V. Grossl",
      "classification": "primary",
      "entity_type": "person",
      "primary": true,
      "person_id": "~{\"name\": \"V. Grossl\"}",
      "organization_id": null
    },
    {
      "name": "K. Jackson",
      "classification": "primary",
      "entity_type": "person",
      "primary": true,
      "person_id": "~{\"name\": \"K. Jackson\"}",
      "organization_id": null
    },
    {
      "name": "D. Lewis",
      "classification": "primary",
      "entity_type": "person",
      "primary": true,
      "person_id": "~{\"name\": \"D. Lewis\"}",
      "organization_id": null
    },
    {
      "name": "B. McCool",
      "classification": "primary",
      "entity_type": "person",
      "primary": true,
      "person_id": "~{\"name\": \"B. McCool\"}",
      "organization_id": null
    },
    {
      "name": "S. Riley",
      "classification": "primary",
      "entity_type": "person",
      "primary": true,
      "person_id": "~{\"name\": \"S. Riley\"}",
      "organization_id": null
    },
    {
      "name": "R. Roarx",
      "classification": "primary",
      "entity_type": "person",
      "primary": true,
      "person_id": "~{\"name\": \"R. Roarx\"}",
      "organization_id": null
    }
  ],
  "related_bills": [],
  "versions": [
    {
      "note": "Introduced",
      "links": [
        {
          "url": "https://apps.legislature.ky.gov/recorddocuments/bill/26RS/hb357/orig_bill.pdf",
          "media_type": "application/pdf"
        }
      ],
      "date": "",
      "classification": ""
    }
  ],
  "documents": [],
  "citations": [],
  "sources": [
    {
      "url": "https://apps.legislature.ky.gov/record/26RS/hb357.html",
      "note": ""
    }
  ],
  "extras": {
    "BDR": "1661"
  },
  "jurisdiction": {
    "id": "ocd-jurisdiction/country:us/state:ky/government",
    "name": "Kentucky",
    "classification": "state",
    "division_id": "ocd-division/country:us/state:ky"
  },
  "_processing": {
    "logs_latest_update": "2026-07-15T13:54:52Z",
    "text_extraction_latest_update": "2026-07-21T07:30:17.505395Z"
  }
}