{
  "legislative_session": "2026RS",
  "identifier": "SR52",
  "title": "A RESOLUTION recognizing July 11, 2026, as Remember Srebrenica Day in Kentucky.",
  "from_organization": "~{\"classification\": \"upper\"}",
  "classification": [
    "resolution"
  ],
  "subject": [
    "Commendations And Recognitions",
    "Crime Victims"
  ],
  "abstracts": [
    {
      "note": "Summary of Original Version",
      "abstract": "Honor Kentucky's Bosnian community and victims of genocide in July 1995 and recognize July 11, 2026, as Remember Srebrenica Day in Kentucky."
    }
  ],
  "other_titles": [],
  "other_identifiers": [
    {
      "identifier": "ocd-bill-ky-2026rs-sr52"
    }
  ],
  "actions": [
    {
      "description": "introduced in Senate",
      "date": "2026-01-22T05:00:00+00:00",
      "organization_id": "~{\"classification\": \"upper\"}",
      "classification": [
        "introduction"
      ],
      "related_entities": [],
      "_processing": {
        "log_file_created": "2026-07-15T13:54:53Z"
      }
    },
    {
      "description": "to Committee on Committees (S)",
      "date": "2026-01-22T05:00:00+00:00",
      "organization_id": "~{\"classification\": \"upper\"}",
      "classification": [
        "referral-committee"
      ],
      "related_entities": [],
      "_processing": {
        "log_file_created": "2026-07-15T13:54:53Z"
      }
    },
    {
      "description": "to Senate Floor",
      "date": "2026-01-27T05:00:00+00:00",
      "organization_id": "~{\"classification\": \"upper\"}",
      "classification": [
        "referral-committee"
      ],
      "related_entities": [],
      "_processing": {
        "log_file_created": "2026-07-15T13:54:53Z"
      }
    },
    {
      "description": "adopted by voice vote",
      "date": "2026-02-05T05:00:00+00:00",
      "organization_id": "~{\"classification\": \"upper\"}",
      "classification": [
        "passage"
      ],
      "related_entities": [],
      "_processing": {
        "log_file_created": "2026-07-15T13:54:53Z"
      }
    }
  ],
  "sponsorships": [
    {
      "name": "M. Wilson",
      "classification": "primary",
      "entity_type": "person",
      "primary": true,
      "person_id": "~{\"name\": \"M. Wilson\"}",
      "organization_id": null
    },
    {
      "name": "M. Wise",
      "classification": "primary",
      "entity_type": "person",
      "primary": true,
      "person_id": "~{\"name\": \"M. Wise\"}",
      "organization_id": null
    },
    {
      "name": "D. Givens",
      "classification": "primary",
      "entity_type": "person",
      "primary": true,
      "person_id": "~{\"name\": \"D. Givens\"}",
      "organization_id": null
    }
  ],
  "related_bills": [],
  "versions": [
    {
      "note": "Current/Final",
      "links": [
        {
          "url": "https://apps.legislature.ky.gov/recorddocuments/bill/26RS/sr52/bill.pdf",
          "media_type": "application/pdf"
        }
      ],
      "date": "",
      "classification": ""
    },
    {
      "note": "Introduced",
      "links": [
        {
          "url": "https://apps.legislature.ky.gov/recorddocuments/bill/26RS/sr52/orig_bill.pdf",
          "media_type": "application/pdf"
        }
      ],
      "date": "",
      "classification": ""
    }
  ],
  "documents": [],
  "citations": [],
  "sources": [
    {
      "url": "https://apps.legislature.ky.gov/record/26RS/sr52.html",
      "note": ""
    }
  ],
  "extras": {
    "BDR": "1638"
  },
  "jurisdiction": {
    "id": "ocd-jurisdiction/country:us/state:ky/government",
    "name": "Kentucky",
    "classification": "state",
    "division_id": "ocd-division/country:us/state:ky"
  },
  "_processing": {
    "logs_latest_update": "2026-07-15T13:54:53Z",
    "text_extraction_latest_update": "2026-07-21T05:42:52.371828Z"
  }
}